Workbook
Name Débutexercicecomptable: 'Trésorerie Prévisionnelle'!$B$4

Sheet Charges à Déduire
A1: =NOW() -> 46145.575
E2: Montant des frais à déduire des revenus fonciers pour 2025 (déclaration 2044)
E3: En vert, les revenus bruts hors TVA
B5: Janvier | C5: Février | D5: Mars | E5: Avril | F5: Mai | G5: Juin | H5: Juillet | I5: Août | J5: Sept. | K5: Oct. | L5: Nov. | M5: Déc. | R5: Demi part
P6: Revenus bruts
A7: Revenus SCI Verdier | B7: 487 | C7: 487 | D7: 487 | E7: 487 | F7: 0 | G7: 0 | H7: 0 | I7: 0 | J7: 0 | K7: 0 | L7: 0 | M7: 0 | P7: =(SUM(B7:M7)) -> 1948 | Q7: Revenus 430
A8: Revenus SCI Colmar (hors TVA) | B8: 0 | C8: 0 | D8: 0 | E8: 0 | F8: 0 | G8: 0 | I8: 0 | J8: 0 | K8: 0 | L8: 0 | M8: 0 | P8: =(SUM(B8:M8)) -> 0 | Q8: Revenus Colmar
A9: Revenus Indivision Bréna | B9: 260 | C9: 260 | D9: 260 | E9: 260 | F9: 0 | G9: 0 | H9: 0 | I9: 0 | J9: 0 | K9: 0 | L9: 0 | M9: 0 | P9: =(SUM(B9:M9)) -> 1040 | Q9: Revenus 526 Bréna
A11: Entretien Espaces verts | B11: 0 | C11: 0 | D11: 0 | E11: 0 | F11: 342 | G11: 342 | H11: 0 | I11: 342 | J11: 0 | K11: 0 | L11: 342 | M11: 0 | O11: =F12+SUM(B11:M11) -> 1368
A12: Assurances PNO SCI (salon) | B12: 0 | C12: 0 | D12: 0 | E12: 0 | O12: 130.67 | P12: =P7+P8 -> 1948 | Q12: Rev. bruts SCI (hors TVA) | R12: =P12/2 -> 974
A13: Assurances PNO indivision hangar | B13: 0 | C13: 0 | D13: 0 | E13: 0 | O13: 300.46 | P13: =P9 -> 1040 | Q13: Rev. bruts indivision | R13: =P13/2 -> 520
A14: Assurance PNO 545 Rodrigues | B14: 25.27 | C14: 25.16 | D14: 25.16 | E14: 25.16 | O14: 261.31 | P14: =P12+P13 -> 2988 | Q14: Total Rev bruts | R14: =P14/2 -> 1494
A15: Total assurances Agen | B15: =SUM(B12:B14) -> 25.27 | C15: =SUM(C12:C14) -> 25.16 | D15: =SUM(D12:D14) -> 25.16 | E15: =SUM(E12:E14) -> 25.16 | F15: =SUM(F12:F14) -> 0 | G15: =SUM(G12:G14) -> 0 | H15: =SUM(H12:H14) -> 0 | I15: =SUM(I12:I14) -> 0 | ... M15: =SUM(M12:M14) -> 0 | O15: =SUM(B15:M15) -> 100.75
A16: Taxes foncières SCI 430 rue Rodrigues | M16: 505
A17: Taxes foncières SCI Avenue de Colmar | M17: 2017 | P17: =O12+M16+M17+40 -> 2692.67 | Q17: Tot frais SCI | R17: =P17/2 -> 1346.335
A18: Taxes foncières 526 rue Rodrigues (Bréna) | M18: 0 | P18: =O13+M18+20 -> 320.46 | Q18: Tot frais indivision | R18: =P18/2 -> 160.23
A19: Frais de banque (pour Cpte Expl) | B19: =9.1+0.75 -> 9.85 | C19: 9.1 | D19: 9.1 | E19: 9.1 | F19: 9.1 | G19: 9.1 | H19: 9.85 | I19: 9.1 | J19: 9.1 | K19: 9.1 | L19: =9.1+0.75 -> 9.85 | M19: =9.1+0.75 -> 9.85 | O19: =SUM(B19:M19) -> 112.2
L20: Revenu net SCI | O20: =P12-P17 -> -744.67 | Q20: Ass PNO SCI | R20: =O12/2 -> 65.335
A21: Taxes foncières indivision 545 | M21: 2238 | Q21: Ass PNO indivision | R21: =(O13)/2 -> 150.23
A22: Frais EDF maison 545 | B22: 21.72 | C22: 0 | D22: 0 | E22: 0 | F22: 0 | G22: 0 | H22: 0 | I22: 0 | J22: 0 | K22: 0 | L22: 0 | M22: 0 | O22: =SUM(B22:M22) -> 21.72
A23: AXEO ménage St Bauzille | B23: 294.7 | C23: 0 | D23: 0 | E23: 0 | F23: 0 | G23: 0 | H23: 0 | I23: 0 | J23: 0 | K23: 0 | L23: 0 | M23: 0 | P23: =SUM(B23:M23)+SUM(G24:M24) -> 294.7 | Q23: Tot frais St Bau
A24: Cesu Sébastien BROSSE | K24: 0
Q25: Taxes foncières SCI | R25: =(M16+M17)/2 -> 1261
A26: Les 2 lignes ci-dessus ne concernent que Saint Bauzille de Montmel | Q26: Taxes foncieres indivis, | R26: 0

Sheet Compte d'Exploitation
C1: Compte d'exploitation | H1: 2026 | L1: =NOW()+30 -> 46175.575
A3: IMPORTANT ====> | B3: Le compte d'exploitation prend en considération tous les encaissements et décaissements du patrimoine que nous possédons à AGEN
B4: (SCI, Entrepôt et frais associés à la maison du 545)
B6: REVENUS | I6: DEPENSES
A8: Trésorerie initiale | B8: 2579.33
A9: SCI Salon | B9: ='Charges à Déduire'!P7 -> 1948 | H9: Entretien | I9: ='Charges à Déduire'!$O$11 -> 1368
H10: EDF | I10: ='Charges à Déduire'!O22 -> 21.72
A11: SCI Colmar | B11: ='Charges à Déduire'!P8 -> 0 | H11: Ass. PNO | I11: ='Charges à Déduire'!O15 -> 100.75
H12: TF Salon | I12: ='Charges à Déduire'!$M$16 -> 505
A13: Indivision Hangar | B13: ='Charges à Déduire'!P13 -> 1040 | H13: TFColmar | I13: ='Charges à Déduire'!$M$17 -> 2017
A14: Remboursement impôts | B14: 0 | H14: TF 545 | I14: ='Charges à Déduire'!$M$21 -> 2238
A15: Apport gérants | B15: 0 | H15: Frais banque | I15: ='Charges à Déduire'!O19 -> 112.2
A16: Vente mobilier | B16: 0 | H16: Remb gérants | I16: 1800
A20: TOTAL | B20: =SUM(B8:B16) -> 5567.33 | I20: =SUM(I9:I19) -> 8162.67
B22: Résultat net comptable | D22: =B20-I20 -> -2595.34

Sheet Bilan
A2: =NOW() +30 -> 46175.575 | E2: Bilan 2026 (Patrimoine AGEN, hors maison 545 rue Rodrigues)
C4: ACTIF | G4: PASSIF
A7: Immobilisations indivision | B7: Terrain | D7: 180000 | F7: Fonds propres | H7: SCI mara47 | I7: Robert | J7: 6 parts | K7: =6*2400 -> 14400
B8: Salon coiffure | D8: 60000 | I8: Michel | J8: 6 parts | K8: =6*2400 -> 14400
B9: Entrepot | D9: 30000 | I9: Laurence | J9: 22 parts | K9: =22*2400 -> 52800
I10: Patrick | J10: 22 parts | K10: =22*2400 -> 52800
A11: Actifs circulants | I11: Candice | J11: 22 parts | K11: =22*2400 -> 52800
B12: Banque | D12: 2579.33 | I12: Yanis | J12: 22 parts | K12: =22*2400 -> 52800
H14: Entrepôt | I14: Michel/Robert | J14: 30000 | K14: 30000
H16: Résultat net comptable | K16: ='Compte d''Exploitation'!D22 -> -2595.34
D21: =SUM(D7:D18) -> 272579.33 | K21: =SUM(K7:K18) -> 267404.66
G22: =D21-K21 -> 5174.67

Sheet Trésorerie Prévisionnelle
B1: Flux de trésorerie Relevé | N1: =NOW() -> 46145.575
B3: Début exercice comptable : | D3: (Pré) démarrage | E3: =UPPER(TEXT(Débutexercicecomptable,"mmm")) -> JANV | F3: =UPPER(TEXT(EOMONTH(Débutexercicecomptable,1),"mmm")) -> FÉVR | G3: =UPPER(TEXT(EOMONTH(Débutexercicecomptable,2),"mmm")) -> MARS | H3: =UPPER(TEXT(EOMONTH(Débutexercicecomptable,3),"mmm")) -> AVR | I3: =UPPER(TEXT(EOMONTH(Débutexercicecomptable,4),"mmm")) -> MAI | J3: =UPPER(TEXT(EOMONTH(Débutexercicecomptable,5),"mmm")) -> JUIN | K3: =UPPER(TEXT(EOMONTH(Débutexercicecomptable,6),"mmm")) -> JUIL | L3: =UPPER(TEXT(EOMONTH(Débutexercicecomptable,7),"mmm")) -> AOÛT | M3: =UPPER(TEXT(EOMONTH(Débutexercicecomptable,8),"mmm")) -> SEPT | N3: =UPPER(TEXT(EOMONTH(Débutexercicecomptable,9),"mmm")) -> OCT | O3: =UPPER(TEXT(EOMONTH(Débutexercicecomptable,10),"mmm")) -> NOV | P3: =UPPER(TEXT(EOMONTH(Débutexercicecomptable,11),"mmm")) -> DÉC | R3: Total
B4: 46023 | D4: Estimation | E4: =Débutexercicecomptable -> 46023 | F4: =EOMONTH(E4,0)+DAY(Débutexercicecomptable) -> 46054 | G4: =EOMONTH(F4,0)+DAY(Débutexercicecomptable) -> 46082 | H4: =EOMONTH(G4,0)+DAY(Débutexercicecomptable) -> 46113 | I4: =EOMONTH(H4,0)+DAY(Débutexercicecomptable) -> 46143 | J4: =EOMONTH(I4,0)+DAY(Débutexercicecomptable) -> 46174 | K4: =EOMONTH(J4,0)+DAY(Débutexercicecomptable) -> 46204 | L4: =EOMONTH(K4,0)+DAY(Débutexercicecomptable) -> 46235 | M4: =EOMONTH(L4,0)+DAY(Débutexercicecomptable) -> 46266 | ... P4: =EOMONTH(O4,0)+DAY(Débutexercicecomptable) -> 46357 | R4: Estimation des éléments
B6: Trésorerie disponible (début du mois) | D6: 2922.08 | E6: =D43 -> 2922.08 | F6: =E43 -> 3608.84 | G6: =F43 -> 4296.46 | H6: =G43 -> 4984.08 | I6: =H43 -> 5329.7 | J6: =I43 -> 5549.69 | K6: =J43 -> 5855.37 | L6: =K43 -> 6503.05 | ... P6: =O43 -> 3649.02 | R6: =P6 -> 3649.02
B8: Encaissements
B10: SCI loyer salon de coiffure | E10: 487 | F10: 487 | G10: 487 | H10: 487 | I10: 487 | J10: 487 | K10: 487 | L10: 487 | M10: 487 | N10: 487 | O10: 487 | P10: 487 | R10: =SUM(Encaissements[[#This Row],[Période 0]:[Période 12]]) -> 5844
B11: SCI loyer terrain av de Colmar | R11: =SUM(Encaissements[[#This Row],[Période 0]:[Période 12]]) -> 0
B12: Indivision loyer hangar | E12: 260 | F12: 260 | G12: 260 | H12: 260 | I12: 260 | J12: 260 | K12: 260 | L12: 260 | M12: 260 | N12: 260 | O12: 260 | P12: 260 | R12: =SUM(Encaissements[[#This Row],[Période 0]:[Période 12]]) -> 3120
B13: Prêts des gérants | R13: =SUM(Encaissements[[#This Row],[Période 0]:[Période 12]]) -> 0
B14: Recettes diverses | R14: =SUM(Encaissements[[#This Row],[Période 0]:[Période 12]]) -> 0
B15: Total | D15: =SUBTOTAL(109,Encaissements[Période 0]) -> 0 | E15: =SUBTOTAL(109,Encaissements[Période 1]) -> 747 | F15: =SUBTOTAL(109,Encaissements[Période 2]) -> 747 | G15: =SUBTOTAL(109,Encaissements[Période 3]) -> 747 | H15: =SUBTOTAL(109,Encaissements[Période 4]) -> 747 | I15: =SUBTOTAL(109,Encaissements[Période 5]) -> 747 | J15: =SUBTOTAL(109,Encaissements[Période 6]) -> 747 | K15: =SUBTOTAL(109,Encaissements[Période 7]) -> 747 | L15: =SUBTOTAL(109,Encaissements[Période 8]) -> 747 | M15: =SUBTOTAL(109,Encaissements[Période 9]) -> 747 | N15: =SUBTOTAL(109,Encaissements[Période 10]) -> 747 | O15: =SUBTOTAL(109,Encaissements[Période 11]) -> 747 | P15: =SUBTOTAL(109,Encaissements[Période 12]) -> 747 | R15: =SUBTOTAL(109,Encaissements[Total]) -> 8964
B16: Total de trésorerie disponible (avant décaissement) | D16: =D6+SUM(Encaissements[Période 0]) -> 2922.08 | E16: =E6+SUM(Encaissements[Période 1]) -> 3669.08 | F16: =F6+SUM(Encaissements[Période 2]) -> 4355.84 | G16: =G6+SUM(Encaissements[Période 3]) -> 5043.46 | H16: =H6+SUM(Encaissements[Période 4]) -> 5731.08 | I16: =I6+SUM(Encaissements[Période 5]) -> 6076.7 | J16: =J6+SUM(Encaissements[Période 6]) -> 6296.69 | K16: =K6+SUM(Encaissements[Période 7]) -> 6602.37 | L16: =L6+SUM(Encaissements[Période 8]) -> 7250.05 | M16: =M6+SUM(Encaissements[Période 9]) -> 7555.73 | N16: =N6+SUM(Encaissements[Période 10]) -> 8203.41 | O16: =O6+SUM(Encaissements[Période 11]) -> 4091.09 | P16: =P6+SUM(Encaissements[Période 12]) -> 4396.02 | R16: =R6+SUM(Encaissements[Total]) -> 12613.02
B18: Décaissements
B20: EDF maison 545 | E20: 25.12 | F20: 25.12 | G20: 25.12 | H20: 25.12 | I20: 25.12 | J20: 25.12 | K20: 25.12 | L20: 25.12 | M20: 25.12 | N20: 25.12 | O20: 25.12 | P20: 25.12 | R20: =SUM(Décaissements[[#This Row],[Période 0]:[Période 12]]) -> 301.44
B21: Toutes assurances pno | E21: 25.27 | F21: 25.16 | G21: 25.16 | H21: 25.16 | I21: =25.16+48.47+77.16 -> 150.79 | J21: =25.16+19.97+19.97 -> 65.1 | K21: =25.16+19.97+19.97 -> 65.1 | L21: =25.16+19.97+19.97 -> 65.1 | M21: =25.16+19.97+19.97 -> 65.1 | N21: =25.16+19.97+19.97 -> 65.1 | O21: =25.16+19.97+19.97 -> 65.1 | P21: =25.16+19.97+19.97 -> 65.1 | R21: =SUM(Décaissements[[#This Row],[Période 0]:[Période 12]]) -> 707.24
B22: Entretien extérieurs | E22: 0 | F22: 0 | G22: 0 | H22: 342 | I22: 342 | J22: 342 | K22: 0 | L22: 342 | M22: 0 | N22: 0 | O22: 342 | P22: 0 | R22: =SUM(Décaissements[[#This Row],[Période 0]:[Période 12]]) -> 1710
B23: Taxe foncière SCI salon | N23: 505 | R23: =SUM(Décaissements[[#This Row],[Période 0]:[Période 12]]) -> 505
B24: Taxe foncière SCI terrain Av de Colmar | N24: 2017 | R24: =SUM(Décaissements[[#This Row],[Période 0]:[Période 12]]) -> 2017
B25: Taxe foncière maison 545 | N25: 2238 | R25: =SUM(Décaissements[[#This Row],[Période 0]:[Période 12]]) -> 2238
B26: Réparations et entretien biens loués | R26: =SUM(Décaissements[[#This Row],[Période 0]:[Période 12]]) -> 0
B27: Remboursement de prêt à la SCI | E27: 0 | F27: 0 | G27: 0 | H27: 0 | I27: 0 | J27: 0 | K27: 0 | L27: 0 | M27: 0 | N27: 0 | O27: 0 | P27: 0 | R27: =SUM(Décaissements[[#This Row],[Période 0]:[Période 12]]) -> 0
B28: Frais de banque | E28: 9.85 | F28: 9.1 | G28: 9.1 | H28: 9.1 | I28: 9.1 | J28: 9.1 | K28: 9.1 | L28: 9.1 | M28: 9.1 | N28: 9.1 | O28: =9.1+0.75 -> 9.85 | P28: =9.1+0.75 -> 9.85 | R28: =SUM(Décaissements[[#This Row],[Période 0]:[Période 12]]) -> 111.45
B29: Prise de Bénéfices par les co-gérants | O29: 0 | P29: 0 | R29: =SUM(Décaissements[[#This Row],[Période 0]:[Période 12]]) -> 0
B30: Divers | R30: =SUM(Décaissements[[#This Row],[Période 0]:[Période 12]]) -> 0
B31: Total | D31: =SUBTOTAL(109,Décaissements[Période 0]) -> 0 | E31: =SUBTOTAL(109,Décaissements[Période 1]) -> 60.24 | F31: =SUBTOTAL(109,Décaissements[Période 2]) -> 59.38 | G31: =SUBTOTAL(109,Décaissements[Période 3]) -> 59.38 | H31: =SUBTOTAL(109,Décaissements[Période 4]) -> 401.38 | I31: =SUBTOTAL(109,Décaissements[Période 5]) -> 527.01 | J31: =SUBTOTAL(109,Décaissements[Période 6]) -> 441.32 | K31: =SUBTOTAL(109,Décaissements[Période 7]) -> 99.32 | L31: =SUBTOTAL(109,Décaissements[Période 8]) -> 441.32 | M31: =SUBTOTAL(109,Décaissements[Période 9]) -> 99.32 | N31: =SUBTOTAL(109,Décaissements[Période 10]) -> 4859.32 | O31: =SUBTOTAL(109,Décaissements[Période 11]) -> 442.07 | P31: =SUBTOTAL(109,Décaissements[Période 12]) -> 100.07 | R31: =SUBTOTAL(109,Décaissements[Total]) -> 7590.13
B33: Décaissements (hors compte de résultat)
B35: Remboursement du capital d’un prêt | R35: =SUM(Décaissements2[[#This Row],[Période 0]:[Période 12]]) -> 0
B36: Achat d’immobilisations (préciser) | R36: =SUM(Décaissements2[[#This Row],[Période 0]:[Période 12]]) -> 0
B37: Autres frais de démarrage | R37: =SUM(Décaissements2[[#This Row],[Période 0]:[Période 12]]) -> 0
B38: Compte sous séquestre | R38: =SUM(Décaissements2[[#This Row],[Période 0]:[Période 12]]) -> 0
B39: Retrait du propriétaire | R39: =SUM(Décaissements2[[#This Row],[Période 0]:[Période 12]]) -> 0
B40: Total | D40: =SUBTOTAL(109,Décaissements2[Période 0]) -> 0 | E40: =SUBTOTAL(109,Décaissements2[Période 1]) -> 0 | F40: =SUBTOTAL(109,Décaissements2[Période 2]) -> 0 | G40: =SUBTOTAL(109,Décaissements2[Période 3]) -> 0 | H40: =SUBTOTAL(109,Décaissements2[Période 4]) -> 0 | I40: =SUBTOTAL(109,Décaissements2[Période 5]) -> 0 | J40: =SUBTOTAL(109,Décaissements2[Période 6]) -> 0 | K40: =SUBTOTAL(109,Décaissements2[Période 7]) -> 0 | L40: =SUBTOTAL(109,Décaissements2[Période 8]) -> 0 | M40: =SUBTOTAL(109,Décaissements2[Période 9]) -> 0 | N40: =SUBTOTAL(109,Décaissements2[Période 10]) -> 0 | O40: =SUBTOTAL(109,Décaissements2[Période 11]) -> 0 | P40: =SUBTOTAL(109,Décaissements2[Période 12]) -> 0 | R40: =SUBTOTAL(109,Décaissements2[Total]) -> 0
B41: Total des décaissements | D41: =SUM(Décaissements[Période 0],Décaissements2[Période 0]) -> 0 | E41: =SUM(Décaissements[Période 1],Décaissements2[Période 1]) -> 60.24 | F41: =SUM(Décaissements[Période 2],Décaissements2[Période 2]) -> 59.38 | G41: =SUM(Décaissements[Période 3],Décaissements2[Période 3]) -> 59.38 | H41: =SUM(Décaissements[Période 4],Décaissements2[Période 4]) -> 401.38 | I41: =SUM(Décaissements[Période 5],Décaissements2[Période 5]) -> 527.01 | J41: =SUM(Décaissements[Période 6],Décaissements2[Période 6]) -> 441.32 | K41: =SUM(Décaissements[Période 7],Décaissements2[Période 7]) -> 99.32 | L41: =SUM(Décaissements[Période 8],Décaissements2[Période 8]) -> 441.32 | M41: =SUM(Décaissements[Période 9],Décaissements2[Période 9]) -> 99.32 | N41: =SUM(Décaissements[Période 10],Décaissements2[Période 10]) -> 4859.32 | O41: =SUM(Décaissements[Période 11],Décaissements2[Période 11]) -> 442.07 | P41: =SUM(Décaissements[Période 12],Décaissements2[Période 12]) -> 100.07 | R41: =SUM(Décaissements[Total],Décaissements2[Total]) -> 7590.13
B43: Position de trésorerie (fin de mois) | D43: =D16-D41 -> 2922.08 | E43: =E16-E41 -> 3608.84 | F43: =F16-F41 -> 4296.46 | G43: =G16-G41 -> 4984.08 | H43: =H16-H41 -> 5329.7 | I43: =I16-I41 -> 5549.69 | J43: =J16-J41 -> 5855.37 | K43: =K16-K41 -> 6503.05 | ... P43: =P16-P41 -> 4295.95 | R43: =R16-R41 -> 5022.89
